unach_photo_server/__init__.py
unach_photo_server/admin.py
unach_photo_server/apps.py
unach_photo_server/forms.py
unach_photo_server/models.py
unach_photo_server/tests.py
unach_photo_server/urls.py
unach_photo_server/views.py
unach_photo_server/migrations/0001_initial.py
unach_photo_server/migrations/0002_auto_20170425_1958.py
unach_photo_server/migrations/0003_photorepository_order.py
unach_photo_server/migrations/0004_auto_20170426_1350.py
unach_photo_server/migrations/0005_auto_20170427_1243.py
unach_photo_server/migrations/0006_photorepository_is_blob.py
unach_photo_server/migrations/0007_auto_20170427_1305.py
unach_photo_server/migrations/__init__.py
unach_photo_server/static/css/unach_photo_server.css
unach_photo_server/static/js/unach_photo_server.js
unach_photo_server/static/unach_photo_server/js/photo-repo-client.js
unach_photo_server/static/unach_photo_server/js/type-repo-field-admin.js
unach_photo_server/templates/unach_photo_server/base.html
unach_photo_server/templates/unach_photo_server/home_test.html
unach_photo_server-0.4.3.dist-info/DESCRIPTION.rst
unach_photo_server-0.4.3.dist-info/METADATA
unach_photo_server-0.4.3.dist-info/RECORD
unach_photo_server-0.4.3.dist-info/WHEEL
unach_photo_server-0.4.3.dist-info/metadata.json
unach_photo_server-0.4.3.dist-info/top_level.txt
