Metadata-Version: 2.0
Name: unach-photo-server
Version: 0.4.3
Summary: Aplicación web encargada de conectar con los repositorios de fotografías dispersos en la unach y generar servicios web para consultar por las fotografías de usuarios.
Home-page: https://github.com/javierhuerta/unach-photo-server
Author: Javier Huerta
Author-email: javierhuerta@unach.cl
License: MIT
Keywords: unach-photo-server
Platform: UNKNOWN
Classifier: Development Status :: 3 - Alpha
Classifier: Framework :: Django
Classifier: Framework :: Django :: 1.10
Classifier: Intended Audience :: Developers
Classifier: License :: OSI Approved :: BSD License
Classifier: Natural Language :: English
Classifier: Programming Language :: Python :: 2
Classifier: Programming Language :: Python :: 2.7
Classifier: Programming Language :: Python :: 3
Classifier: Programming Language :: Python :: 3.4
Classifier: Programming Language :: Python :: 3.5
Requires-Dist: MySQL-python (>=1.2.5)
Requires-Dist: django-model-utils (>=2.0)
Requires-Dist: pysmb (>=1.1.19)
